{
  "controlled_email_delivery": {
    "advisory_disclaimer": "This controlled email delivery contract is repo-only fixture output for preview review. It is advisory-only and does not authorize email sending, SMTP, Gmail API, LINE, dashboard deployment, trading, portfolio action, or external system mutation.",
    "approval_gate": {
      "approval_required": true,
      "current_review_status": "pending_review",
      "delivery_allowed": false,
      "gate_id": "controlled_email_delivery_approval_gate_v1",
      "gate_open": false,
      "reason": "Email delivery remains blocked until review_status is approved and delivery_allowed is true.",
      "required_review_status": "approved",
      "source_gate_id": "delivery_payload_builder_approval_gate_v1",
      "source_gate_open": false
    },
    "attachments_preview": [],
    "body_preview": {
      "contains_full_email_body": false,
      "explainability_ref_count": 2,
      "format": "text_preview_refs",
      "payload_id": "delivery_payload_2026-06-30",
      "preview_id": "daily_report_static_preview_20260630",
      "preview_text": "Delivery preview is blocked until the approval gate is open.",
      "review_id": "daily_report_preview_review_20260630",
      "source_run_id": "delivery-payload-builder-fixture-20260630"
    },
    "delivery_allowed": false,
    "delivery_blockers": [
      "approval_gate_closed",
      "email_channel_disabled",
      "fixture_mode_no_email_send",
      "human_review_required",
      "review_status_not_approved",
      "warning_badges_present"
    ],
    "email_channel_enabled": false,
    "email_delivery_id": "controlled_email_delivery_2026-06-30",
    "human_review_required": true,
    "payload_id": "delivery_payload_2026-06-30",
    "preview_only": true,
    "recipients_policy": {
      "allow_external_recipients": false,
      "policy_id": "controlled_email_recipients_policy_v1",
      "recipient_count": 0,
      "recipients_resolved": false,
      "requires_explicit_runtime_configuration": true,
      "resolution_mode": "fixture_redacted"
    },
    "report_date": "2026-06-30",
    "review_id": "daily_report_preview_review_20260630",
    "review_status": "pending_review",
    "send_intent": "preview_only_no_send",
    "send_status": "not_sent",
    "subject_preview": "Daily Report Preview 2026-06-30",
    "warning_badges": [
      {
        "badge_id": "daily_report_preview_card_20260630_warning_1",
        "label": "forecast review source reports insufficient data",
        "severity": "warning",
        "source": "preview_review_workflow"
      },
      {
        "badge_id": "daily_report_preview_card_20260630_warning_2",
        "label": "human review required for one or more intelligence sources",
        "severity": "warning",
        "source": "preview_review_workflow"
      },
      {
        "badge_id": "daily_report_preview_card_20260630_warning_3",
        "label": "one or more source credibility records require human review",
        "severity": "warning",
        "source": "preview_review_workflow"
      },
      {
        "badge_id": "daily_report_preview_card_20260630_warning_4",
        "label": "source renderer completed with warnings",
        "severity": "warning",
        "source": "preview_review_workflow"
      },
      {
        "badge_id": "daily_report_preview_card_20260630_warning_5",
        "label": "source research pack completed with warnings",
        "severity": "warning",
        "source": "preview_review_workflow"
      },
      {
        "badge_id": "delivery_payload_explainability_warning_credibility_risk_explanations_present",
        "label": "credibility_risk_explanations_present",
        "severity": "warning",
        "source": "forecast_explainability_layer"
      },
      {
        "badge_id": "delivery_payload_explainability_warning_human_review_required_explanations_present",
        "label": "human_review_required_explanations_present",
        "severity": "warning",
        "source": "forecast_explainability_layer"
      }
    ]
  },
  "decision": "email_delivery_blocked_pending_approval",
  "email_delivery_summary": {
    "attachment_count": 0,
    "decision": "email_delivery_blocked_pending_approval",
    "delivery_allowed": false,
    "delivery_blocker_count": 6,
    "deterministic_output": true,
    "email_channel_enabled": false,
    "email_delivery_id": "controlled_email_delivery_2026-06-30",
    "generated_at": "2026-06-30T10:45:00+08:00",
    "human_review_required": true,
    "mode": "fixture_dry_run",
    "ok": true,
    "payload_id": "delivery_payload_2026-06-30",
    "preview_only": true,
    "recipient_count": 0,
    "report_date": "2026-06-30",
    "review_id": "daily_report_preview_review_20260630",
    "review_status": "pending_review",
    "run_id": "controlled-email-delivery-fixture-20260630",
    "safety": {
      "advisory_only": true,
      "api_server_created": false,
      "dashboard_deploy": false,
      "fixture_only": true,
      "no_dashboard_deploy": true,
      "no_delivery_actions": true,
      "no_email_send": true,
      "no_external_model_calls": true,
      "no_gmail_api_call": true,
      "no_line_push": true,
      "no_market_data_calls": true,
      "no_persistent_store_writes": true,
      "no_portfolio_actions": true,
      "no_schedule_service_changes": true,
      "no_smtp_call": true,
      "preview_only": true,
      "repo_only": true,
      "trading_instruction": false
    },
    "schema_version": "controlled_email_delivery_summary_v1",
    "send_intent": "preview_only_no_send",
    "send_status": "not_sent",
    "task_id": "AI-DEV-094",
    "warning_badge_count": 7
  },
  "generated_at": "2026-06-30T10:45:00+08:00",
  "mode": "fixture_dry_run",
  "next_recommendation": "Keep email delivery blocked until an approved review fixture exists; do not send email or call SMTP/Gmail APIs.",
  "ok": true,
  "run_id": "controlled-email-delivery-fixture-20260630",
  "safety": {
    "advisory_only": true,
    "api_server_created": false,
    "dashboard_deploy": false,
    "fixture_only": true,
    "no_dashboard_deploy": true,
    "no_delivery_actions": true,
    "no_email_send": true,
    "no_external_model_calls": true,
    "no_gmail_api_call": true,
    "no_line_push": true,
    "no_market_data_calls": true,
    "no_persistent_store_writes": true,
    "no_portfolio_actions": true,
    "no_schedule_service_changes": true,
    "no_smtp_call": true,
    "preview_only": true,
    "repo_only": true,
    "trading_instruction": false
  },
  "schema_version": "controlled_email_delivery_contract_v1",
  "side_effects": {
    "called_external_model_runtime": false,
    "called_gmail_api": false,
    "called_market_data_runtime": false,
    "called_smtp": false,
    "created_api_server": false,
    "deployed_dashboard": false,
    "modified_github_remote": false,
    "modified_portfolio": false,
    "modified_schedule_or_service": false,
    "placed_trade_order": false,
    "read_secrets": false,
    "sent_email": false,
    "sent_line_push": false,
    "sent_notification": false,
    "wrote_persistent_store": false
  },
  "task_id": "AI-DEV-094",
  "validation_summary": {
    "approval_gate_required": true,
    "attachments_preview_only": true,
    "contract_name": "controlled_email_delivery",
    "contract_version": "v1",
    "delivery_allowed_policy_enforced": true,
    "delivery_blocker_count": 6,
    "deterministic_output": true,
    "email_channel_policy_enforced": true,
    "fixture_only": true,
    "preview_only": true,
    "recipients_unresolved": true,
    "send_intent_preview_only": true,
    "send_status_not_sent": true,
    "source_ok": true,
    "source_schema_matched": true,
    "warning_count": 7,
    "warnings": [
      "forecast review source reports insufficient data",
      "human review required for one or more intelligence sources",
      "one or more source credibility records require human review",
      "source renderer completed with warnings",
      "source research pack completed with warnings",
      "credibility_risk_explanations_present",
      "human_review_required_explanations_present"
    ]
  }
}
